diz/__init__.py
diz/main.py
diz/commands/__init__.py
diz/commands/install.py
diz/commands/setup.py
diz/commands/shell.py
diz/utils/__init__.py
diz/utils/dir.py
diz/utils/download.py
diz/utils/pip.py
diz/utils/shell.py
diz/utils/validators.py
diz/utils/venv.py
diz/utils/yaml.py
tests/__init__.py
tests/utils/__init__.py
tests/utils/test_dir.py
tests/utils/test_shell.py
tests/utils/test_validators.py
tests/utils/test_venv.py
diz-1.0.2.dist-info/METADATA
diz-1.0.2.dist-info/WHEEL
diz-1.0.2.dist-info/entry_points.txt
diz-1.0.2.dist-info/top_level.txt
diz-1.0.2.dist-info/RECORD
