Metadata-Version: 2.1
Name: diz
Version: 1.0.2
Summary: 用来构建大模型环境的工具
Author: mjason
Requires-Dist: GitPython (>=3.1.31)
Requires-Dist: huggingface-hub (>=0.16.4)
Requires-Dist: PyYAML (>=6.0)
Requires-Dist: requests (>=2.31.0)
Requires-Dist: toolz (>=0.12.0)
Requires-Dist: typer (>=0.9.0)
Requires-Dist: libtmux (>=0.20.0)
Requires-Dist: PyGithub (>=1.50)
